rpi_bad_power/__init__.py
rpi_bad_power-0.1.0.dist-info/LICENSE
rpi_bad_power-0.1.0.dist-info/METADATA
rpi_bad_power-0.1.0.dist-info/WHEEL
rpi_bad_power-0.1.0.dist-info/top_level.txt
rpi_bad_power-0.1.0.dist-info/RECORD
