Metadata-Version: 2.1
Name: rpi-bad-power
Version: 0.1.0
Summary: A Python library to detect bad power supply on Raspberry Pi .
Home-page: https://github.com/shenxn/rpi-bad-power
Author: Xiaonan Shen
Author-email: s@sxn.dev
License: MIT License
Keywords: rpi,raspberry-pi
Platform: any
Classifier: Programming Language :: Python :: 3
Classifier: Intended Audience :: Developers
Classifier: License :: OSI Approved :: MIT License
Classifier: Operating System :: POSIX :: Linux
Classifier: Programming Language :: Python :: 3.7
Classifier: Topic :: Software Development :: Embedded Systems
